eth_seher/__init__.py
eth_seher/cli.py
eth_seher/interceptor.py
eth_seher/monitor.py
eth_seher/submit_tx.py
eth_seher/trace.py
eth_seher-1.1.2.dist-info/licenses/LICENSE
eth_seher-1.1.2.dist-info/METADATA
eth_seher-1.1.2.dist-info/WHEEL
eth_seher-1.1.2.dist-info/entry_points.txt
eth_seher-1.1.2.dist-info/top_level.txt
eth_seher-1.1.2.dist-info/RECORD
